senselab/__init__.py
senselab/agentic_interface/__init__.py
senselab/agentic_interface/doc.md
senselab/agentic_interface/launcher.py
senselab/agentic_interface/nbi-config.json
senselab/agentic_interface/senselab_agent/__init__.py
senselab/agentic_interface/senselab_agent/extension.json
senselab/agentic_interface/senselab_agent/extension.py
senselab/agentic_interface/senselab_agent/install.py
senselab/agentic_interface/senselab_agent/notebook_share_tool.py
senselab/audio/__init__.py
senselab/audio/data_structures/__init__.py
senselab/audio/data_structures/audio.py
senselab/audio/data_structures/audio_classification_result.py
senselab/audio/tasks/__init__.py
senselab/audio/tasks/classification/__init__.py
senselab/audio/tasks/classification/api.py
senselab/audio/tasks/classification/doc.md
senselab/audio/tasks/classification/huggingface.py
senselab/audio/tasks/classification/speech_emotion_recognition/__init__.py
senselab/audio/tasks/classification/speech_emotion_recognition/api.py
senselab/audio/tasks/classification/speech_emotion_recognition/doc.md
senselab/audio/tasks/data_augmentation/__init__.py
senselab/audio/tasks/data_augmentation/api.py
senselab/audio/tasks/data_augmentation/audiomentations.py
senselab/audio/tasks/data_augmentation/doc.md
senselab/audio/tasks/data_augmentation/torch_audiomentations.py
senselab/audio/tasks/features_extraction/__init__.py
senselab/audio/tasks/features_extraction/api.py
senselab/audio/tasks/features_extraction/doc.md
senselab/audio/tasks/features_extraction/opensmile.py
senselab/audio/tasks/features_extraction/ppg.py
senselab/audio/tasks/features_extraction/praat_parselmouth.py
senselab/audio/tasks/features_extraction/sparc.py
senselab/audio/tasks/features_extraction/torchaudio.py
senselab/audio/tasks/features_extraction/torchaudio_squim.py
senselab/audio/tasks/forced_alignment/__init__.py
senselab/audio/tasks/forced_alignment/constants.py
senselab/audio/tasks/forced_alignment/data_structures.py
senselab-1.3.0.dist-info/METADATA
senselab-1.3.0.dist-info/WHEEL
senselab-1.3.0.dist-info/entry_points.txt
senselab-1.3.0.dist-info/licenses/LICENSE.md
senselab-1.3.0.dist-info/RECORD
