Metadata-Version: 2.4
Name: senselab
Version: 1.3.0
Summary: senselab is a Python package that simplifies building pipelines for speech and voice analysis.
License: # LICENSE
License-File: LICENSE.md
Keywords: audio,voice,speech,video,pose,face,text,nlp
Author: Fabio Catania
Author-email: fabiocat@mit.edu
Maintainer: Fabio Catania
Maintainer-email: fabiocat@mit.edu
Requires-Python: >=3.11,<3.13
Classifier: Development Status :: 3 - Alpha
Classifier: Programming Language :: Python :: 3.11
Classifier: Programming Language :: Python :: 3.12
Classifier: License :: OSI Approved :: Apache Software License
Classifier: Operating System :: OS Independent
Provides-Extra: articulatory
Provides-Extra: senselab-ai
Provides-Extra: text
Provides-Extra: video
Requires-Dist: accelerate
Requires-Dist: audiomentations (>=0.42,<1.0)
Requires-Dist: av (>=15,<15.1) ; extra == "video"
Requires-Dist: coqui-tts (>=0.27,<1.0)
Requires-Dist: datasets (>=3.6,<4.0)
Requires-Dist: huggingface-hub (>=0.34,<1.0)
Requires-Dist: ipykernel (>=7.1,<8.0) ; extra == "senselab-ai"
Requires-Dist: ipywidgets (>=8.1,<9.0) ; extra == "senselab-ai"
Requires-Dist: iso639 (>=0.1,<1.0)
Requires-Dist: joblib (>=1.5,<2.0)
Requires-Dist: jupyterlab (>=4.4,<5.0) ; extra == "senselab-ai"
Requires-Dist: lightning (>=2.4.0,<2.5.0)
Requires-Dist: matplotlib (>=3.10,<4.0)
Requires-Dist: nbformat (>=5.10,<6.0) ; extra == "senselab-ai"
Requires-Dist: nbss-upload (>=0.1,<1.0) ; extra == "senselab-ai"
Requires-Dist: nest-asyncio (>=1.6,<2.0)
Requires-Dist: notebook-intelligence (>=2.3.2,<2.4.0) ; extra == "senselab-ai"
Requires-Dist: opencv-python-headless (>=4.11,<5.0) ; extra == "video"
Requires-Dist: opensmile (>=2.6,<3.0)
Requires-Dist: ppgs (>=0.0.9,<0.0.10)
Requires-Dist: praat-parselmouth (>=0.4,<1.0)
Requires-Dist: pyannote-audio (>=4,<4.1)
Requires-Dist: pycountry (>=24.6,<25.0)
Requires-Dist: pydantic (>=2.11,<3.0)
Requires-Dist: pylangacq (>=0.19,<1.0) ; extra == "text"
Requires-Dist: python-ffmpeg (>=2.0,<3.0)
Requires-Dist: scikit-learn (>=1.7,<2.0)
Requires-Dist: sentence-transformers (>=5.1,<6.0) ; extra == "text"
Requires-Dist: snorkel (>=0.10.0,<0.11.0)
Requires-Dist: speech-articulatory-coding (>=0.1,<1.0) ; extra == "articulatory"
Requires-Dist: speechbrain (>=1,<1.1)
Requires-Dist: torch (>=2.8.0,<2.9.0) ; sys_platform != "darwin" or platform_machine == "arm64"
Requires-Dist: torch-audiomentations (>=0.12,<1.0)
Requires-Dist: torchaudio (>=2.8.0,<2.9.0)
Requires-Dist: torchcodec (>=0.7.0,<0.8.0)
Requires-Dist: torchvision (>=0.23.0,<0.24.0)
Requires-Dist: transformers (>=4.53.3,<4.54.0)
Requires-Dist: ultralytics (>=8.3,<9.0) ; extra == "video"
Requires-Dist: umap-learn (>=0.5,<1.0)
Requires-Dist: vocos (>=0.1,<1.0)
